xplor/__init__.py
xplor/_dependencies.py
xplor/_utils.py
xplor/gurobi/__init__.py
xplor/gurobi/model.py
xplor/hexaly/__init__.py
xplor/hexaly/model.py
xplor/mathopt/__init__.py
xplor/mathopt/model.py
xplor/model.py
xplor/obj_expr.py
xplor/types.py
xplor/var_expr.py
xplor-0.3.1.dist-info/WHEEL
xplor-0.3.1.dist-info/METADATA
xplor-0.3.1.dist-info/RECORD
