Metadata-Version: 2.3
Name: xplor
Version: 0.3.1
Summary: A unified framework for Operation Research modeling with polars
Keywords: optimization,polars,gurobi,mathopt,operations research
Author: Gabriel Robin
License: MIT
Requires-Dist: polars>=1.35
Requires-Dist: xplor[gurobi] ; extra == 'all'
Requires-Dist: xplor[ortools] ; extra == 'all'
Requires-Dist: xplor[hexaly] ; extra == 'all'
Requires-Dist: gurobipy>=11.0.3 ; extra == 'gurobi'
Requires-Dist: numpy>=2.1.2 ; extra == 'gurobi'
Requires-Dist: hexaly>=14.0.20251203 ; extra == 'hexaly'
Requires-Dist: ortools>=9.11.4210 ; extra == 'ortools'
Requires-Python: >=3.11
Project-URL: Bug Tracker, https://github.com/gab23r/xplor/issues
Project-URL: Documentation, https://gab23r.github.io/xplor/
Project-URL: Homepage, https://github.com/gab23r/xplor
Project-URL: Repository, https://github.com/gab23r/xplor
Provides-Extra: all
Provides-Extra: gurobi
Provides-Extra: hexaly
Provides-Extra: ortools
